flask_table2/__init__.py
flask_table2/columns.py
flask_table2/compat.py
flask_table2/html.py
flask_table2/table.py
flask_table2-0.1.0.dist-info/licenses/LICENSE
flask_table2-0.1.0.dist-info/METADATA
flask_table2-0.1.0.dist-info/WHEEL
flask_table2-0.1.0.dist-info/top_level.txt
flask_table2-0.1.0.dist-info/RECORD
