Metadata-Version: 2.4
Name: Flask-Table2
Version: 0.1.0
Summary: HTML tables for use with the Flask micro-framework
Home-page: https://github.com/TonyRolfe/flask_table
Author: Tony Rolfe
Author-email: tony.rolfe@ibm.com
Classifier: Development Status :: 3 - Alpha
Classifier: Programming Language :: Python
Classifier: Programming Language :: Python :: 2
Classifier: Programming Language :: Python :: 2.7
Classifier: Programming Language :: Python :: 3
Classifier: Programming Language :: Python :: 3.3
Classifier: Programming Language :: Python :: 3.4
Classifier: Operating System :: OS Independent
Classifier: Framework :: Flask
License-File: LICENSE
Requires-Dist: Flask
Requires-Dist: Flask-Babel
Dynamic: author
Dynamic: author-email
Dynamic: classifier
Dynamic: home-page
Dynamic: license-file
Dynamic: requires-dist
Dynamic: summary
